abs_lexorank/__init__.py
abs_lexorank/lexorank_service.py
abs_lexorank-0.2.0.dist-info/METADATA
abs_lexorank-0.2.0.dist-info/WHEEL
abs_lexorank-0.2.0.dist-info/RECORD
