Metadata-Version: 2.3
Name: abs-lexorank
Version: 0.2.0
Summary: A lexorank core library that provide all lexorank related base classes and utilities
Author: divy551
Author-email: divydedakiya5@gmail.com
Requires-Python: >=3.11,<4.0
Classifier: Programming Language :: Python :: 3
Classifier: Programming Language :: Python :: 3.11
Classifier: Programming Language :: Python :: 3.12
Classifier: Programming Language :: Python :: 3.13
